{
  "AWSTemplateFormatVersion": "2010-09-09",
  "Description": "An auto-generated nested stack.",
  "Metadata": {},
  "Parameters": {
    "AppSyncApiId": {
      "Type": "String",
      "Description": "The id of the AppSync API associated with this project."
    },
    "AppSyncApiName": {
      "Type": "String",
      "Description": "The name of the AppSync API",
      "Default": "AppSyncSimpleTransform"
    },
    "env": {
      "Type": "String",
      "Description": "The environment name. e.g. Dev, Test, or Production",
      "Default": "NONE"
    },
    "S3DeploymentBucket": {
      "Type": "String",
      "Description": "The S3 bucket containing all deployment assets for the project."
    },
    "S3DeploymentRootKey": {
      "Type": "String",
      "Description": "An S3 key relative to the S3DeploymentBucket that points to the root\nof the deployment directory."
    }
  },
  "Resources": {
    "EmptyResource": {
      "Type": "Custom::EmptyResource",
      "Condition": "AlwaysFalse"
    },
    "StartLambdaDataSource": {
      "Type": "AWS::AppSync::DataSource",
      "Properties": {
        "ApiId": {
          "Ref": "AppSyncApiId"
        },
        "Name": "StartFunction",
        "Type": "AWS_LAMBDA",
        "ServiceRoleArn": {
          "Fn::GetAtt": ["StartLambdaDataSourceRole", "Arn"]
        },
        "LambdaConfig": {
          "LambdaFunctionArn": {
            "Fn::Sub": [
              "arn:aws:lambda:${AWS::Region}:${AWS::AccountId}:function:ec2start-${env}",
              {
                "env": {
                  "Ref": "env"
                }
              }
            ]
          }
        }
      }
    },
    "StartLambdaDataSourceRole": {
      "Type": "AWS::IAM::Role",
      "Properties": {
        "RoleName": {
          "Fn::Sub": [
            "StartLambdaDataSourceRole-${env}",
            {
              "env": {
                "Ref": "env"
              }
            }
          ]
        },
        "AssumeRolePolicyDocument": {
          "Version": "2012-10-17",
          "Statement": [
            {
              "Effect": "Allow",
              "Principal": {
                "Service": "appsync.amazonaws.com"
              },
              "Action": "sts:AssumeRole"
            }
          ]
        },
        "Policies": [
          {
            "PolicyName": "InvokeLambdaFunction",
            "PolicyDocument": {
              "Version": "2012-10-17",
              "Statement": [
                {
                  "Effect": "Allow",
                  "Action": ["lambda:invokeFunction"],
                  "Resource": [
                    {
                      "Fn::Sub": [
                        "arn:aws:lambda:${AWS::Region}:${AWS::AccountId}:function:ec2start-${env}",
                        {
                          "env": {
                            "Ref": "env"
                          }
                        }
                      ]
                    }
                  ]
                }
              ]
            }
          }
        ]
      }
    },
    "QueryStartResolver": {
      "Type": "AWS::AppSync::Resolver",
      "Properties": {
        "ApiId": {
          "Ref": "AppSyncApiId"
        },
        "DataSourceName": {
          "Fn::GetAtt": ["StartLambdaDataSource", "Name"]
        },
        "TypeName": "Query",
        "FieldName": "start",
        "RequestMappingTemplateS3Location": {
          "Fn::Sub": [
            "s3://${S3DeploymentBucket}/${S3DeploymentRootKey}/resolvers/Query.start.req.vtl",
            {
              "S3DeploymentBucket": {
                "Ref": "S3DeploymentBucket"
              },
              "S3DeploymentRootKey": {
                "Ref": "S3DeploymentRootKey"
              }
            }
          ]
        },
        "ResponseMappingTemplateS3Location": {
          "Fn::Sub": [
            "s3://${S3DeploymentBucket}/${S3DeploymentRootKey}/resolvers/Query.start.res.vtl",
            {
              "S3DeploymentBucket": {
                "Ref": "S3DeploymentBucket"
              },
              "S3DeploymentRootKey": {
                "Ref": "S3DeploymentRootKey"
              }
            }
          ]
        }
      }
    },
    "TerminateLambdaDataSource": {
      "Type": "AWS::AppSync::DataSource",
      "Properties": {
        "ApiId": {
          "Ref": "AppSyncApiId"
        },
        "Name": "TerminateFunction",
        "Type": "AWS_LAMBDA",
        "ServiceRoleArn": {
          "Fn::GetAtt": ["TerminateLambdaDataSourceRole", "Arn"]
        },
        "LambdaConfig": {
          "LambdaFunctionArn": {
            "Fn::Sub": [
              "arn:aws:lambda:${AWS::Region}:${AWS::AccountId}:function:ec2terminate-${env}",
              {
                "env": {
                  "Ref": "env"
                }
              }
            ]
          }
        }
      }
    },
    "TerminateLambdaDataSourceRole": {
      "Type": "AWS::IAM::Role",
      "Properties": {
        "RoleName": {
          "Fn::Sub": [
            "TerminateLambdaDataSourceRole-${env}",
            {
              "env": {
                "Ref": "env"
              }
            }
          ]
        },
        "AssumeRolePolicyDocument": {
          "Version": "2012-10-17",
          "Statement": [
            {
              "Effect": "Allow",
              "Principal": {
                "Service": "appsync.amazonaws.com"
              },
              "Action": "sts:AssumeRole"
            }
          ]
        },
        "Policies": [
          {
            "PolicyName": "InvokeLambdaFunction",
            "PolicyDocument": {
              "Version": "2012-10-17",
              "Statement": [
                {
                  "Effect": "Allow",
                  "Action": ["lambda:invokeFunction"],
                  "Resource": [
                    {
                      "Fn::Sub": [
                        "arn:aws:lambda:${AWS::Region}:${AWS::AccountId}:function:ec2terminate-${env}",
                        {
                          "env": {
                            "Ref": "env"
                          }
                        }
                      ]
                    }
                  ]
                }
              ]
            }
          }
        ]
      }
    },
    "QueryTerminateResolver": {
      "Type": "AWS::AppSync::Resolver",
      "Properties": {
        "ApiId": {
          "Ref": "AppSyncApiId"
        },
        "DataSourceName": {
          "Fn::GetAtt": ["TerminateLambdaDataSource", "Name"]
        },
        "TypeName": "Query",
        "FieldName": "terminate",
        "RequestMappingTemplateS3Location": {
          "Fn::Sub": [
            "s3://${S3DeploymentBucket}/${S3DeploymentRootKey}/resolvers/Query.terminate.req.vtl",
            {
              "S3DeploymentBucket": {
                "Ref": "S3DeploymentBucket"
              },
              "S3DeploymentRootKey": {
                "Ref": "S3DeploymentRootKey"
              }
            }
          ]
        },
        "ResponseMappingTemplateS3Location": {
          "Fn::Sub": [
            "s3://${S3DeploymentBucket}/${S3DeploymentRootKey}/resolvers/Query.terminate.req.vtl",
            {
              "S3DeploymentBucket": {
                "Ref": "S3DeploymentBucket"
              },
              "S3DeploymentRootKey": {
                "Ref": "S3DeploymentRootKey"
              }
            }
          ]
        }
      }
    },
    "UpdateTrainerLambdaDataSource": {
      "Type": "AWS::AppSync::DataSource",
      "Properties": {
        "ApiId": {
          "Ref": "AppSyncApiId"
        },
        "Name": "UpdateTrainerFunction",
        "Type": "AWS_LAMBDA",
        "ServiceRoleArn": {
          "Fn::GetAtt": ["UpdateTrainerLambdaDataSourceRole", "Arn"]
        },
        "LambdaConfig": {
          "LambdaFunctionArn": {
            "Fn::Sub": [
              "arn:aws:lambda:${AWS::Region}:${AWS::AccountId}:function:updatetrainerdata-${env}",
              {
                "env": {
                  "Ref": "env"
                }
              }
            ]
          }
        }
      }
    },
    "UpdateTrainerLambdaDataSourceRole": {
      "Type": "AWS::IAM::Role",
      "Properties": {
        "RoleName": {
          "Fn::Sub": [
            "UpdateTrainerLambdaDataSourceRole-${env}",
            {
              "env": {
                "Ref": "env"
              }
            }
          ]
        },
        "AssumeRolePolicyDocument": {
          "Version": "2012-10-17",
          "Statement": [
            {
              "Effect": "Allow",
              "Principal": {
                "Service": "appsync.amazonaws.com"
              },
              "Action": "sts:AssumeRole"
            }
          ]
        },
        "Policies": [
          {
            "PolicyName": "InvokeLambdaFunction",
            "PolicyDocument": {
              "Version": "2012-10-17",
              "Statement": [
                {
                  "Effect": "Allow",
                  "Action": ["lambda:invokeFunction"],
                  "Resource": [
                    {
                      "Fn::Sub": [
                        "arn:aws:lambda:${AWS::Region}:${AWS::AccountId}:function:updatetrainerdata-${env}",
                        {
                          "env": {
                            "Ref": "env"
                          }
                        }
                      ]
                    }
                  ]
                }
              ]
            }
          }
        ]
      }
    },
    "QueryUpdateTrainerResolver": {
      "Type": "AWS::AppSync::Resolver",
      "Properties": {
        "ApiId": {
          "Ref": "AppSyncApiId"
        },
        "DataSourceName": {
          "Fn::GetAtt": ["UpdateTrainerLambdaDataSource", "Name"]
        },
        "TypeName": "Query",
        "FieldName": "updateTrainer",
        "RequestMappingTemplateS3Location": {
          "Fn::Sub": [
            "s3://${S3DeploymentBucket}/${S3DeploymentRootKey}/resolvers/Query.updatetrainer.req.vtl",
            {
              "S3DeploymentBucket": {
                "Ref": "S3DeploymentBucket"
              },
              "S3DeploymentRootKey": {
                "Ref": "S3DeploymentRootKey"
              }
            }
          ]
        },
        "ResponseMappingTemplateS3Location": {
          "Fn::Sub": [
            "s3://${S3DeploymentBucket}/${S3DeploymentRootKey}/resolvers/Query.updatetrainer.req.vtl",
            {
              "S3DeploymentBucket": {
                "Ref": "S3DeploymentBucket"
              },
              "S3DeploymentRootKey": {
                "Ref": "S3DeploymentRootKey"
              }
            }
          ]
        }
      }
    },
    "DownloadTrainerLambdaDataSource": {
      "Type": "AWS::AppSync::DataSource",
      "Properties": {
        "ApiId": {
          "Ref": "AppSyncApiId"
        },
        "Name": "DownloadTrainerFunction",
        "Type": "AWS_LAMBDA",
        "ServiceRoleArn": {
          "Fn::GetAtt": ["DownloadTrainerLambdaDataSourceRole", "Arn"]
        },
        "LambdaConfig": {
          "LambdaFunctionArn": {
            "Fn::Sub": [
              "arn:aws:lambda:${AWS::Region}:${AWS::AccountId}:function:downloadtrainerdata-${env}",
              {
                "env": {
                  "Ref": "env"
                }
              }
            ]
          }
        }
      }
    },
    "DownloadTrainerLambdaDataSourceRole": {
      "Type": "AWS::IAM::Role",
      "Properties": {
        "RoleName": {
          "Fn::Sub": [
            "DownloadTrainerLambdaDataSourceRole-${env}",
            {
              "env": {
                "Ref": "env"
              }
            }
          ]
        },
        "AssumeRolePolicyDocument": {
          "Version": "2012-10-17",
          "Statement": [
            {
              "Effect": "Allow",
              "Principal": {
                "Service": "appsync.amazonaws.com"
              },
              "Action": "sts:AssumeRole"
            }
          ]
        },
        "Policies": [
          {
            "PolicyName": "InvokeLambdaFunction",
            "PolicyDocument": {
              "Version": "2012-10-17",
              "Statement": [
                {
                  "Effect": "Allow",
                  "Action": ["lambda:invokeFunction"],
                  "Resource": [
                    {
                      "Fn::Sub": [
                        "arn:aws:lambda:${AWS::Region}:${AWS::AccountId}:function:downloadtrainerdata-${env}",
                        {
                          "env": {
                            "Ref": "env"
                          }
                        }
                      ]
                    }
                  ]
                }
              ]
            }
          }
        ]
      }
    },
    "QueryDownloadTrainerResolver": {
      "Type": "AWS::AppSync::Resolver",
      "Properties": {
        "ApiId": {
          "Ref": "AppSyncApiId"
        },
        "DataSourceName": {
          "Fn::GetAtt": ["DownloadTrainerLambdaDataSource", "Name"]
        },
        "TypeName": "Query",
        "FieldName": "downloadTrainer",
        "RequestMappingTemplateS3Location": {
          "Fn::Sub": [
            "s3://${S3DeploymentBucket}/${S3DeploymentRootKey}/resolvers/Query.downloadtrainer.req.vtl",
            {
              "S3DeploymentBucket": {
                "Ref": "S3DeploymentBucket"
              },
              "S3DeploymentRootKey": {
                "Ref": "S3DeploymentRootKey"
              }
            }
          ]
        },
        "ResponseMappingTemplateS3Location": {
          "Fn::Sub": [
            "s3://${S3DeploymentBucket}/${S3DeploymentRootKey}/resolvers/Query.downloadtrainer.res.vtl",
            {
              "S3DeploymentBucket": {
                "Ref": "S3DeploymentBucket"
              },
              "S3DeploymentRootKey": {
                "Ref": "S3DeploymentRootKey"
              }
            }
          ]
        }
      }
    }
  },
  "Conditions": {
    "HasEnvironmentParameter": {
      "Fn::Not": [
        {
          "Fn::Equals": [
            {
              "Ref": "env"
            },
            "NONE"
          ]
        }
      ]
    },
    "AlwaysFalse": {
      "Fn::Equals": ["true", "false"]
    }
  },
  "Outputs": {
    "EmptyOutput": {
      "Description": "An empty output. You may delete this if you have at least one resource above.",
      "Value": ""
    }
  }
}
